{
    "output_dir": "dataStorage",
    "cache": "cache",
    "model_output": "dataStorage/model_output",
    "dissimilarity_folder": "cache/dissimilarity_arrays",
    "cka_matrices_folder": "cache/cka_matrices",
    "embedding_folder": "dataStorage/model_output/embedding",
    "std_output_folder": "dataStorage/model_output/std_output",
    "rsaData": "dataStorage/rsaData",
    "ckaData": "dataStorage/ckaData",
    "processedResults": "dataStorage/processedResults",
    "cosineDissimilarity": "cache/dissimilarity_arrays/cosineDissimilarity.csv",
    "classes": "classes.csv",
    "datasetClasses": "dataStorage/datasetClasses.csv",
    "selectedIndices": "dataStorage/selectedIndices.csv",
    "validation_results": "dataStorage/validation_results.csv",
    "modelOutput": "dataStorage/model_output/modelOutput.csv",
    "runData": "./dataStorage/rsaData/runData.csv",
    "fst_embedding_path": "./dataStorage/model_output/embedding/efficientnet_b4_IMAGENET1K_V1_torchvision_fgvc-aircraft(0).pt",
    "snd_embedding_path": "./dataStorage/model_output/embedding/efficientnet_b7_IMAGENET1K_V1_torchvision_fgvc-aircraft(0).pt"
}